LICENSE.rst
MANIFEST.in
README.md
setup.py
docs/TODO.html
fedex_invoice/__init__.py
fedex_invoice/invoice.py
fedex_invoice.egg-info/PKG-INFO
fedex_invoice.egg-info/SOURCES.txt
fedex_invoice.egg-info/dependency_links.txt
fedex_invoice.egg-info/requires.txt
fedex_invoice.egg-info/top_level.txt
test/test_todo.py