Metadata-Version: 1.1
Name: fedex-invoice
Version: 1.0.1
Summary: Fedex Commercial Invoice generator, invoice templating using reportlab
Home-page: https://github.com/radzhome/fedex-commercial-invoice/
Author: radzhome
Author-email: radzhome@gmail.com
License: BSD
Download-URL: TODO
Keywords: fedex commercial invoice generator using reportlab
Platform: Platform Independent
Classifier: Development Status :: 5 - Production/Stable
Classifier: Intended Audience :: Developers
Classifier: License :: OSI Approved :: BSD License
Classifier: Natural Language :: English
Classifier: Operating System :: OS Independent
Classifier: Programming Language :: Python
Classifier: Topic :: Software Development :: Libraries :: Python Modules
